FontMap/HuiFontMap.py
FontMap/__init__.py
FontMap-1.1.10.dist-info/LICENSE
FontMap-1.1.10.dist-info/METADATA
FontMap-1.1.10.dist-info/WHEEL
FontMap-1.1.10.dist-info/top_level.txt
FontMap-1.1.10.dist-info/RECORD
