Metadata-Version: 2.1
Name: FontMap
Version: 1.1.10
Summary: A tool library for generating mapping dictionaries based on font files
Home-page: https://github.com/HuiHui-lin/FontMap
Author: HuiHui
Author-email: 2176189493@qq.com
Classifier: Programming Language :: Python :: 3
Classifier: License :: OSI Approved :: MIT License
Requires-Python: >=3.8
License-File: LICENSE
